README.md
setup.py
asyncio_request_limiter/RequestsPerHostLimiter.py
asyncio_request_limiter/RequestsPerTokenLimiter.py
asyncio_request_limiter/__init__.py
asyncio_request_limiter.egg-info/PKG-INFO
asyncio_request_limiter.egg-info/SOURCES.txt
asyncio_request_limiter.egg-info/dependency_links.txt
asyncio_request_limiter.egg-info/top_level.txt